{
    "version": "https://jsonfeed.org/version/1",
    "title": "WHAT WE DO :: TRANSLATION :: TRANSCREATION :: LOCALIZATION COPYWRITING :: GERMAN TO ENGLISH :: FRENCH TO ENGLISH",
    "description": "",
    "home_page_url": "https://yuighj99.github.io/trans-blog",
    "feed_url": "https://yuighj99.github.io/trans-blog/feed.json",
    "user_comment": "",
    "author": {
        "name": "Manko Pie"
    },
    "items": [
        {
            "id": "https://yuighj99.github.io/trans-blog/machine-translation.html",
            "url": "https://yuighj99.github.io/trans-blog/machine-translation.html",
            "title": "Isn&#x27;t machine translation good enough these days?",
            "summary": "Well, it is good for some things. It's good for email exchanges or translating on the fly out of another&hellip;",
            "content_html": "<p>Well, it is good for some things. It's good for email exchanges or translating on the fly out of another language into yours. Situations where all parties concerned know that they will need to work a little to understand what is meant, and where it is acceptable that some things won't be immediately clear (or may even be completely unclear).</p>",
            "image": "https://yuighj99.github.io/trans-blog/media/posts/6/french-to-english-2.png",
            "author": {
                "name": "Manko Pie"
            },
            "tags": [
            ],
            "date_published": "2022-07-01T18:36:21+02:00",
            "date_modified": "2022-07-02T14:22:04+02:00"
        },
        {
            "id": "https://yuighj99.github.io/trans-blog/what-is-transcreation.html",
            "url": "https://yuighj99.github.io/trans-blog/what-is-transcreation.html",
            "title": "WHAT IS TRANSCREATION?",
            "summary": "Transcreation is a word we hear quite often these days, but maybe the term \"localization copywriting\" is a little more&hellip;",
            "content_html": "<p>Transcreation is a word we hear quite often these days, but maybe the term \"localization copywriting\" is a little more self-explanatory. Call it what you like, it is the process of not just translating text but rewriting a message in another language and, where necessary, adapting it culturally.</p>",
            "image": "https://yuighj99.github.io/trans-blog/media/posts/5/02900_cadaques.JPG",
            "author": {
                "name": "Manko Pie"
            },
            "tags": [
            ],
            "date_published": "2022-07-01T12:28:19+02:00",
            "date_modified": "2022-07-01T12:47:07+02:00"
        },
        {
            "id": "https://yuighj99.github.io/trans-blog/translate-this.html",
            "url": "https://yuighj99.github.io/trans-blog/translate-this.html",
            "title": "Would you translate this as &quot;In a train to Tirol&quot;?",
            "summary": "I have seen this sign many times and always admired the excellent wordplay. As far as I know there is&hellip;",
            "content_html": "<p>I have seen this sign many times and always admired the excellent wordplay. As far as I know there is no English version, and I don't think there needs to be. I think it is mainly aimed at Germans driving through a part of Tirol in Austria. But it is a great exercise. \"In a train to Tirol\" would be an obvious translation that a normal translator would be tempted to use. But it would lose that wonderful wordplay and turn a very clever strapline into something completely flat.</p>\n<p>But what could we use instead?</p>",
            "image": "https://yuighj99.github.io/trans-blog/media/posts/1/b2fb6fa8-3525-541f-9d28-3d6cd54fd938.webp",
            "author": {
                "name": "Manko Pie"
            },
            "tags": [
            ],
            "date_published": "2022-07-01T10:02:16+02:00",
            "date_modified": "2022-07-01T13:33:26+02:00"
        },
        {
            "id": "https://yuighj99.github.io/trans-blog/customers-want-clarity.html",
            "url": "https://yuighj99.github.io/trans-blog/customers-want-clarity.html",
            "title": "Customers want clarity",
            "summary": "Your marketing message must be crystal clear. There are too many voices out there to waste time trying to figure&hellip;",
            "content_html": "<p>Your marketing message must be crystal clear. There are too many voices out there to waste time trying to figure out what someone who is trying to sell something means. Who will bother?</p>",
            "image": "https://yuighj99.github.io/trans-blog/media/posts/2/IMG_1876-2.JPG",
            "author": {
                "name": "Manko Pie"
            },
            "tags": [
            ],
            "date_published": "2022-06-01T10:27:00+02:00",
            "date_modified": "2022-07-01T11:25:45+02:00"
        }
    ]
}
